arxiv_tracker/__init__.py
arxiv_tracker/query_tracker.py
arxiv_tracker/rss_tracker.py
arxiv_tracker-0.0.2.dist-info/METADATA
arxiv_tracker-0.0.2.dist-info/WHEEL
arxiv_tracker-0.0.2.dist-info/top_level.txt
arxiv_tracker-0.0.2.dist-info/RECORD
