Metadata-Version: 2.4
Name: arxiv-tracker
Version: 0.0.2
Summary: A tool for tracking new papers on arXiv
Project-URL: Homepage, https://github.com/monkitect/arxiv_tracker
Project-URL: Repository, https://github.com/monkitect/arxiv_tracker
Project-URL: Issues, https://github.com/monkitect/arxiv_tracker/issues
Requires-Dist: feedparser
Requires-Dist: pandas
